mediapills/__init__.py
mediapills/console/__init__.py
mediapills/console/applications.py
mediapills/console/arguments.py
mediapills/console/exceptions.py
mediapills/console/inputs.py
mediapills/console/outputs.py
mediapills/console/parsers.py
mediapills.console-0.0.1.dist-info/LICENSE.md
mediapills.console-0.0.1.dist-info/METADATA
mediapills.console-0.0.1.dist-info/WHEEL
mediapills.console-0.0.1.dist-info/top_level.txt
mediapills.console-0.0.1.dist-info/zip-safe
mediapills.console-0.0.1.dist-info/RECORD
